{
  "date": "24-Apr-2026",
  "fii_buy": 9837.2,
  "fii_sell": 18665.07,
  "fii_net": -8827.87,
  "dii_buy": 21560.16,
  "dii_sell": 16859.45,
  "dii_net": 4700.71,
  "fetched_at": "2026-04-24T14:13:32.708341+00:00",
  "raw": [
    {
      "category": "DII",
      "date": "24-Apr-2026",
      "buyValue": "21560.16",
      "sellValue": "16859.45",
      "netValue": "4700.71"
    },
    {
      "category": "FII/FPI",
      "date": "24-Apr-2026",
      "buyValue": "9837.2",
      "sellValue": "18665.07",
      "netValue": "-8827.87"
    }
  ],
  "nifty_price": 23897.95,
  "nifty_change": -275.1,
  "nifty_change_pct": -1.14,
  "vix_price": 19.71,
  "vix_change_pct": 6.03
}